arcade_miro_api/__init__.py
arcade_miro_api/tools/__init__.py
arcade_miro_api/tools/request_body_schemas.py
arcade_miro_api/wrapper_tools/AddAppCardToBoard.json
arcade_miro_api/wrapper_tools/AddBoardFrame.json
arcade_miro_api/wrapper_tools/AddCardToMiroBoard.json
arcade_miro_api/wrapper_tools/AddConnectorToBoard.json
arcade_miro_api/wrapper_tools/AddDocumentToBoardByUrl.json
arcade_miro_api/wrapper_tools/AddEmbedItemToBoard.json
arcade_miro_api/wrapper_tools/AddFlowchartShapeToBoard.json
arcade_miro_api/wrapper_tools/AddImageToMiroBoard.json
arcade_miro_api/wrapper_tools/AddItemsToMiroBoard.json
arcade_miro_api/wrapper_tools/AddMindmapNode.json
arcade_miro_api/wrapper_tools/AddMiroProjectMember.json
arcade_miro_api/wrapper_tools/AddShapeToMiroBoard.json
arcade_miro_api/wrapper_tools/AddStickyNoteToBoard.json
arcade_miro_api/wrapper_tools/AddTextToMiroBoard.json
arcade_miro_api/wrapper_tools/AttachTagToItem.json
arcade_miro_api/wrapper_tools/CopyMiroBoard.json
arcade_miro_api/wrapper_tools/CreateBoardExportJob.json
arcade_miro_api/wrapper_tools/CreateBoardSubscription.json
arcade_miro_api/wrapper_tools/CreateBoardTag.json
arcade_miro_api/wrapper_tools/CreateEnterpriseProject.json
arcade_miro_api/wrapper_tools/CreateEnterpriseTeam.json
arcade_miro_api/wrapper_tools/CreateGroupOnBoard.json
arcade_miro_api/wrapper_tools/CreateMiroBoard.json
arcade_miro_api/wrapper_tools/DeleteAppCardFromBoard.json
arcade_miro_api/wrapper_tools/DeleteBoardConnector.json
arcade_miro_api/wrapper_tools/DeleteBoardFrame.json
arcade_miro_api/wrapper_tools/DeleteBoardGroup.json
arcade_miro_api/wrapper_tools/DeleteBoardImage.json
arcade_miro_api/wrapper_tools/DeleteBoardItem.json
arcade_miro_api/wrapper_tools/DeleteBoardTag.json
arcade_miro_api/wrapper_tools/DeleteBoardTextItem.json
arcade_miro_api/wrapper_tools/DeleteCardFromBoard.json
arcade_miro_api/wrapper_tools/DeleteCardItem.json
arcade_miro_api/wrapper_tools/DeleteDocumentItemFromBoard.json
arcade_miro_api-3.0.0.dist-info/METADATA
arcade_miro_api-3.0.0.dist-info/WHEEL
arcade_miro_api-3.0.0.dist-info/entry_points.txt
arcade_miro_api-3.0.0.dist-info/licenses/LICENSE
arcade_miro_api-3.0.0.dist-info/RECORD
